habana_frameworks/medialoaders/__init__.py
habana_frameworks/medialoaders/tensorflow/__init__.py
habana_frameworks/medialoaders/tensorflow/media_resnet_pipe.py
habana_frameworks/medialoaders/torch/__init__.py
habana_frameworks/medialoaders/torch/media_dataloader_mediapipe.py
habana_frameworks/medialoaders/torch/mediapipe_unet_3d.py
habana_frameworks/medialoaders/torch/mediapipe_unet_mlperf.py
habana_frameworks/medialoaders/torch/mediapipe_unet_mlperf_cpp.py
habana_frameworks/mediapipe/__init__.py
habana_frameworks/mediapipe/fn.py
habana_frameworks/mediapipe/media_proxy.py
habana_frameworks/mediapipe/media_types.py
habana_frameworks/mediapipe/mediapipe.py
habana_frameworks/mediapipe/backend/__init__.py
habana_frameworks/mediapipe/backend/cal.py
habana_frameworks/mediapipe/backend/graph.py
habana_frameworks/mediapipe/backend/graph_cpu.py
habana_frameworks/mediapipe/backend/iterator.py
habana_frameworks/mediapipe/backend/legacy.py
habana_frameworks/mediapipe/backend/logger.py
habana_frameworks/mediapipe/backend/nodes.py
habana_frameworks/mediapipe/backend/operator_specs.py
habana_frameworks/mediapipe/backend/proxy_impl.py
habana_frameworks/mediapipe/backend/tensor.py
habana_frameworks/mediapipe/backend/tensor_cpu.py
habana_frameworks/mediapipe/backend/tracing.py
habana_frameworks/mediapipe/backend/utils.py
habana_frameworks/mediapipe/operators/__init__.py
habana_frameworks/mediapipe/operators/media_nodes.py
habana_frameworks/mediapipe/operators/media_params.py
habana_frameworks/mediapipe/operators/media_schema.py
habana_frameworks/mediapipe/operators/cpu_nodes/__init__.py
habana_frameworks/mediapipe/operators/cpu_nodes/basic_crop.py
habana_frameworks/mediapipe/operators/cpu_nodes/cpu_node_params.py
habana_frameworks/mediapipe/operators/cpu_nodes/cpu_node_schema.py
habana_frameworks/mediapipe/operators/cpu_nodes/cpu_nodes.py
habana_frameworks/mediapipe/operators/cpu_nodes/cpu_ops_node.py
habana_frameworks/mediapipe/operators/cpu_nodes/random_biased_crop.py
hpu_media_loader-1.9.0.580.1.dist-info/LICENSE.txt
hpu_media_loader-1.9.0.580.1.dist-info/METADATA
hpu_media_loader-1.9.0.580.1.dist-info/WHEEL
hpu_media_loader-1.9.0.580.1.dist-info/top_level.txt
hpu_media_loader-1.9.0.580.1.dist-info/RECORD
