Metadata-Version: 2.1
Name: hpu-media-loader
Version: 1.9.0.580.1
Summary: Dataloader using Habana hardware media pipeline
Home-page: https://habana.ai/
Author: Habana Labs Ltd., an Intel Company
Author-email: support@habana.ai
License: See LICENSE.txt
Platform: UNKNOWN
License-File: LICENSE.txt
Requires-Dist: pillow
